toybox/__init__.py
toybox/base.py
toybox/forcings.py
toybox/integrators.py
toybox/nonlinearities.py
toybox/premade.py
MDOF_toybox-0.2.2.dist-info/LICENSE
MDOF_toybox-0.2.2.dist-info/METADATA
MDOF_toybox-0.2.2.dist-info/WHEEL
MDOF_toybox-0.2.2.dist-info/top_level.txt
MDOF_toybox-0.2.2.dist-info/RECORD
