Metadata-Version: 2.1
Name: MDOF-toybox
Version: 0.2.2
Summary: Tooling to generate toy MDOF dynamics data for arbitrary linear and nonlinear systems in python
Home-page: https://github.com/MDCHAMP/Toybox
Author: Max Champneys
Author-email: max.champneys@gmail.com
License: MIT
Platform: UNKNOWN
Classifier: License :: OSI Approved :: MIT License
Classifier: Programming Language :: Python :: 3.8
License-File: LICENSE
Requires-Dist: numpy
